LICENSE.txt
MANIFEST.in
README.md
setup.py
objectextensions/__init__.py
objectextensions/extendable.py
objectextensions/extension.py
objectextensions/methods.py
objectextensions.egg-info/PKG-INFO
objectextensions.egg-info/SOURCES.txt
objectextensions.egg-info/dependency_links.txt
objectextensions.egg-info/requires.txt
objectextensions.egg-info/top_level.txt