Metadata-Version: 2.1
Name: objectextensions
Version: 2.0.3
Summary: A basic framework for implementing an extension pattern
Home-page: https://github.com/immijimmi/objectextensions
Download-URL: https://github.com/immijimmi/objectextensions/archive/refs/tags/v2.0.3.tar.gz
Author: immijimmi
Author-email: immijimmi1@gmail.com
License: MIT
Keywords: extensions,plugins
Classifier: Development Status :: 4 - Beta
Classifier: Intended Audience :: Developers
Classifier: Topic :: Software Development :: Libraries :: Application Frameworks
Classifier: License :: OSI Approved :: MIT License
Classifier: Programming Language :: Python :: 3.11
License-File: LICENSE.txt
Requires-Dist: wrapt~=1.15.0
